pymbusparser-0.0.4.dist-info/METADATA
pymbusparser-0.0.4.dist-info/WHEEL
pymbusparser/__init__.py
pymbusparser/pymbusparser.pypy39-pp73-arm-linux-gnu.so
pymbusparser-0.0.4.dist-info/RECORD
