Metadata-Version: 2.4
Name: pymbusparser
Version: 0.0.4
Summary: Python bindings for m-bus-parser written in Rust
Home-Page: https://maebli.github.io/
Author: Michael Aebli
License: MIT
Project-URL: Source Code, https://github.com/maebli/m-bus-parser
